gordion/__init__.py
gordion/analogs.py
gordion/cache.py
gordion/exception.py
gordion/repository.py
gordion/tree.py
gordion/utils.py
gordion/workspace.py
gordion/yeditor.py
gordion/app/__init__.py
gordion/app/main.py
gordion/app/status/__init__.py
gordion/app/status/folder.py
gordion/app/status/repository_folder.py
gordion/app/status/terminal_status.py
gordion-1.0.3.dist-info/METADATA
gordion-1.0.3.dist-info/WHEEL
gordion-1.0.3.dist-info/entry_points.txt
gordion-1.0.3.dist-info/licenses/LICENSE
gordion-1.0.3.dist-info/licenses/NOTICE
gordion-1.0.3.dist-info/RECORD
