Metadata-Version: 2.3
Name: gordion
Version: 1.0.3
Summary: A multi-repository management tool with a git-like command interface
Project-URL: Homepage, https://github.com/jacob-heathorn/gordion
Author-email: Jacob Heathorn <jacob.heathorn@gmail.com>
License: MIT
Keywords: dependencies,git,management,repository,workspace
Classifier: License :: OSI Approved :: MIT License
Classifier: Operating System :: MacOS :: MacOS X
Classifier: Operating System :: Microsoft :: Windows
Classifier: Operating System :: POSIX :: Linux
Classifier: Programming Language :: Python :: 3
Requires-Python: >=3.8
Requires-Dist: gitpython==3.1.43
Requires-Dist: pyyaml
Requires-Dist: types-pyyaml
